assistant/__init__.py
kaia_assistant-0.0.0.dist-info/METADATA
kaia_assistant-0.0.0.dist-info/WHEEL
kaia_assistant-0.0.0.dist-info/top_level.txt
kaia_assistant-0.0.0.dist-info/RECORD
